include/actuator.h
include/asio.hpp
include/asio/any_completion_executor.hpp
include/asio/any_completion_handler.hpp
include/asio/any_io_executor.hpp
include/asio/append.hpp
include/asio/as_tuple.hpp
include/asio/associated_allocator.hpp
include/asio/associated_cancellation_slot.hpp
include/asio/associated_executor.hpp
include/asio/associated_immediate_executor.hpp
include/asio/associator.hpp
include/asio/async_result.hpp
include/asio/awaitable.hpp
include/asio/basic_datagram_socket.hpp
include/asio/basic_deadline_timer.hpp
include/asio/basic_file.hpp
include/asio/basic_io_object.hpp
include/asio/basic_random_access_file.hpp
include/asio/basic_raw_socket.hpp
include/asio/basic_readable_pipe.hpp
include/asio/basic_seq_packet_socket.hpp
include/asio/basic_serial_port.hpp
include/asio/basic_signal_set.hpp
include/asio/basic_socket.hpp
include/asio/basic_socket_acceptor.hpp
include/asio/basic_socket_iostream.hpp
include/asio/basic_socket_streambuf.hpp
include/asio/basic_stream_file.hpp
include/asio/basic_stream_socket.hpp
include/asio/basic_streambuf.hpp
include/asio/basic_streambuf_fwd.hpp
include/asio/basic_waitable_timer.hpp
include/asio/basic_writable_pipe.hpp
include/asio/bind_allocator.hpp
include/asio/bind_cancellation_slot.hpp
include/asio/bind_executor.hpp
include/asio/bind_immediate_executor.hpp
include/asio/buffer.hpp
include/asio/buffer_registration.hpp
include/asio/buffered_read_stream.hpp
include/asio/buffered_read_stream_fwd.hpp
include/asio/buffered_stream.hpp
include/asio/buffered_stream_fwd.hpp
include/asio/buffered_write_stream.hpp
include/asio/buffered_write_stream_fwd.hpp
include/asio/buffers_iterator.hpp
include/asio/cancel_after.hpp
include/asio/cancel_at.hpp
include/asio/cancellation_signal.hpp
include/asio/cancellation_state.hpp
include/asio/cancellation_type.hpp
include/asio/co_composed.hpp
include/asio/co_spawn.hpp
include/asio/completion_condition.hpp
include/asio/compose.hpp
pyorcasdk-1.1.0.dist-info/METADATA
pyorcasdk-1.1.0.dist-info/WHEEL
pyorcasdk-1.1.0.dist-info/RECORD
pyorcasdk-1.1.0.dist-info/licenses/LICENSE
