Metadata-Version: 2.2
Name: pyorcasdk
Version: 1.1.0
Summary: Python bindings for the C++ orcaSDK library
Author-Email: "Iris Dynamics Ltd." <support@irisdynamics.com>
License:                                  Apache License
Project-URL: source, https://github.com/IrisDynamics/pyorcasdk
Project-URL: documentation, https://github.com/IrisDynamics/pyorcasdk/releases/download/v1.1.0/pyorcasdk-docs.zip
Project-URL: tutorials, https://github.com/IrisDynamics/orcaSDK_tutorials
Requires-Python: >=3.8
